{
  "schema_version": "2025-03-09",
  "generated_at": "2026-03-19T23:17:45.493005Z",
  "season": 2026,
  "sims": 5000,
  "teams": [
    "Michigan Wolverines",
    "UMBC Retrievers",
    "Howard Bison",
    "Georgia Bulldogs",
    "Saint Louis Billikens",
    "Texas Tech Red Raiders",
    "Akron Zips",
    "Alabama Crimson Tide",
    "Hofstra Pride",
    "Tennessee Volunteers",
    "Miami OH RedHawks",
    "SMU Mustangs",
    "Virginia Cavaliers",
    "Wright State Raiders",
    "Kentucky Wildcats",
    "Santa Clara Broncos",
    "Iowa State Cyclones",
    "Tennessee State Tigers",
    "Duke Blue Devils",
    "Siena Saints",
    "Ohio State Buckeyes",
    "TCU Horned Frogs",
    "St. John's Red Storm",
    "Northern Iowa Panthers",
    "Kansas Jayhawks",
    "California Baptist Lancers",
    "Louisville Cardinals",
    "South Florida Bulls",
    "Michigan State Spartans",
    "North Dakota State Bison",
    "UCLA Bruins",
    "UCF Knights",
    "UConn Huskies",
    "Furman Paladins",
    "Arizona Wildcats",
    "Long Island University Sharks",
    "Villanova Wildcats",
    "Utah State Aggies",
    "Wisconsin Badgers",
    "High Point Panthers",
    "Arkansas Razorbacks",
    "Hawai'i Rainbow Warriors",
    "BYU Cougars",
    "Texas Longhorns",
    "NC State Wolfpack",
    "Gonzaga Bulldogs",
    "Kennesaw State Owls",
    "Miami Hurricanes",
    "Missouri Tigers",
    "Purdue Boilermakers",
    "Queens University Royals",
    "Florida Gators",
    "Prairie View A&M Panthers",
    "Lehigh Mountain Hawks",
    "Clemson Tigers",
    "Iowa Hawkeyes",
    "Vanderbilt Commodores",
    "McNeese Cowboys",
    "Nebraska Cornhuskers",
    "Troy Trojans",
    "North Carolina Tar Heels",
    "VCU Rams",
    "Illinois Fighting Illini",
    "Pennsylvania Quakers",
    "Saint Mary's Gaels",
    "Texas A&M Aggies",
    "Houston Cougars",
    "Idaho Vandals"
  ],
  "bracket_source": "official_ncaa",
  "bracket": [
    {
      "slot": 1,
      "team": "Michigan Wolverines",
      "seed": 1,
      "region": "Midwest"
    },
    {
      "slot": 2,
      "team": "UMBC Retrievers",
      "seed": 16,
      "region": "Midwest"
    },
    {
      "slot": 3,
      "team": "Georgia Bulldogs",
      "seed": 8,
      "region": "Midwest"
    },
    {
      "slot": 4,
      "team": "Saint Louis Billikens",
      "seed": 9,
      "region": "Midwest"
    },
    {
      "slot": 5,
      "team": "Texas Tech Red Raiders",
      "seed": 5,
      "region": "Midwest"
    },
    {
      "slot": 6,
      "team": "Akron Zips",
      "seed": 12,
      "region": "Midwest"
    },
    {
      "slot": 7,
      "team": "Alabama Crimson Tide",
      "seed": 4,
      "region": "Midwest"
    },
    {
      "slot": 8,
      "team": "Hofstra Pride",
      "seed": 13,
      "region": "Midwest"
    },
    {
      "slot": 9,
      "team": "Tennessee Volunteers",
      "seed": 6,
      "region": "Midwest"
    },
    {
      "slot": 10,
      "team": "Miami OH RedHawks",
      "seed": 11,
      "region": "Midwest"
    },
    {
      "slot": 11,
      "team": "Virginia Cavaliers",
      "seed": 3,
      "region": "Midwest"
    },
    {
      "slot": 12,
      "team": "Wright State Raiders",
      "seed": 14,
      "region": "Midwest"
    },
    {
      "slot": 13,
      "team": "Kentucky Wildcats",
      "seed": 7,
      "region": "Midwest"
    },
    {
      "slot": 14,
      "team": "Santa Clara Broncos",
      "seed": 10,
      "region": "Midwest"
    },
    {
      "slot": 15,
      "team": "Iowa State Cyclones",
      "seed": 2,
      "region": "Midwest"
    },
    {
      "slot": 16,
      "team": "Tennessee State Tigers",
      "seed": 15,
      "region": "Midwest"
    },
    {
      "slot": 17,
      "team": "Duke Blue Devils",
      "seed": 1,
      "region": "East"
    },
    {
      "slot": 18,
      "team": "Siena Saints",
      "seed": 16,
      "region": "East"
    },
    {
      "slot": 19,
      "team": "Ohio State Buckeyes",
      "seed": 8,
      "region": "East"
    },
    {
      "slot": 20,
      "team": "TCU Horned Frogs",
      "seed": 9,
      "region": "East"
    },
    {
      "slot": 21,
      "team": "St. John's Red Storm",
      "seed": 5,
      "region": "East"
    },
    {
      "slot": 22,
      "team": "Northern Iowa Panthers",
      "seed": 12,
      "region": "East"
    },
    {
      "slot": 23,
      "team": "Kansas Jayhawks",
      "seed": 4,
      "region": "East"
    },
    {
      "slot": 24,
      "team": "California Baptist Lancers",
      "seed": 13,
      "region": "East"
    },
    {
      "slot": 25,
      "team": "Louisville Cardinals",
      "seed": 6,
      "region": "East"
    },
    {
      "slot": 26,
      "team": "South Florida Bulls",
      "seed": 11,
      "region": "East"
    },
    {
      "slot": 27,
      "team": "Michigan State Spartans",
      "seed": 3,
      "region": "East"
    },
    {
      "slot": 28,
      "team": "North Dakota State Bison",
      "seed": 14,
      "region": "East"
    },
    {
      "slot": 29,
      "team": "UCLA Bruins",
      "seed": 7,
      "region": "East"
    },
    {
      "slot": 30,
      "team": "UCF Knights",
      "seed": 10,
      "region": "East"
    },
    {
      "slot": 31,
      "team": "UConn Huskies",
      "seed": 2,
      "region": "East"
    },
    {
      "slot": 32,
      "team": "Furman Paladins",
      "seed": 15,
      "region": "East"
    },
    {
      "slot": 33,
      "team": "Arizona Wildcats",
      "seed": 1,
      "region": "West"
    },
    {
      "slot": 34,
      "team": "Long Island University Sharks",
      "seed": 16,
      "region": "West"
    },
    {
      "slot": 35,
      "team": "Villanova Wildcats",
      "seed": 8,
      "region": "West"
    },
    {
      "slot": 36,
      "team": "Utah State Aggies",
      "seed": 9,
      "region": "West"
    },
    {
      "slot": 37,
      "team": "Wisconsin Badgers",
      "seed": 5,
      "region": "West"
    },
    {
      "slot": 38,
      "team": "High Point Panthers",
      "seed": 12,
      "region": "West"
    },
    {
      "slot": 39,
      "team": "Arkansas Razorbacks",
      "seed": 4,
      "region": "West"
    },
    {
      "slot": 40,
      "team": "Hawai'i Rainbow Warriors",
      "seed": 13,
      "region": "West"
    },
    {
      "slot": 41,
      "team": "BYU Cougars",
      "seed": 6,
      "region": "West"
    },
    {
      "slot": 42,
      "team": "NC State Wolfpack",
      "seed": 11,
      "region": "West"
    },
    {
      "slot": 43,
      "team": "Gonzaga Bulldogs",
      "seed": 3,
      "region": "West"
    },
    {
      "slot": 44,
      "team": "Kennesaw State Owls",
      "seed": 14,
      "region": "West"
    },
    {
      "slot": 45,
      "team": "Miami Hurricanes",
      "seed": 7,
      "region": "West"
    },
    {
      "slot": 46,
      "team": "Missouri Tigers",
      "seed": 10,
      "region": "West"
    },
    {
      "slot": 47,
      "team": "Purdue Boilermakers",
      "seed": 2,
      "region": "West"
    },
    {
      "slot": 48,
      "team": "Queens University Royals",
      "seed": 15,
      "region": "West"
    },
    {
      "slot": 49,
      "team": "Florida Gators",
      "seed": 1,
      "region": "South"
    },
    {
      "slot": 50,
      "team": "Lehigh Mountain Hawks",
      "seed": 16,
      "region": "South"
    },
    {
      "slot": 51,
      "team": "Clemson Tigers",
      "seed": 8,
      "region": "South"
    },
    {
      "slot": 52,
      "team": "Iowa Hawkeyes",
      "seed": 9,
      "region": "South"
    },
    {
      "slot": 53,
      "team": "Vanderbilt Commodores",
      "seed": 5,
      "region": "South"
    },
    {
      "slot": 54,
      "team": "McNeese Cowboys",
      "seed": 12,
      "region": "South"
    },
    {
      "slot": 55,
      "team": "Nebraska Cornhuskers",
      "seed": 4,
      "region": "South"
    },
    {
      "slot": 56,
      "team": "Troy Trojans",
      "seed": 13,
      "region": "South"
    },
    {
      "slot": 57,
      "team": "North Carolina Tar Heels",
      "seed": 6,
      "region": "South"
    },
    {
      "slot": 58,
      "team": "VCU Rams",
      "seed": 11,
      "region": "South"
    },
    {
      "slot": 59,
      "team": "Illinois Fighting Illini",
      "seed": 3,
      "region": "South"
    },
    {
      "slot": 60,
      "team": "Pennsylvania Quakers",
      "seed": 14,
      "region": "South"
    },
    {
      "slot": 61,
      "team": "Saint Mary's Gaels",
      "seed": 7,
      "region": "South"
    },
    {
      "slot": 62,
      "team": "Texas A&M Aggies",
      "seed": 10,
      "region": "South"
    },
    {
      "slot": 63,
      "team": "Houston Cougars",
      "seed": 2,
      "region": "South"
    },
    {
      "slot": 64,
      "team": "Idaho Vandals",
      "seed": 15,
      "region": "South"
    }
  ],
  "first_four": [
    {
      "slot": 2,
      "teamA": "UMBC Retrievers",
      "teamB": "Howard Bison",
      "seedA": 16,
      "seedB": 16,
      "region": "Midwest",
      "prob_a": 0.6336,
      "prob_b": 0.3664
    },
    {
      "slot": 10,
      "teamA": "Miami OH RedHawks",
      "teamB": "SMU Mustangs",
      "seedA": 11,
      "seedB": 11,
      "region": "Midwest",
      "prob_a": 0.6779,
      "prob_b": 0.3221
    },
    {
      "slot": 42,
      "teamA": "Texas Longhorns",
      "teamB": "NC State Wolfpack",
      "seedA": 11,
      "seedB": 11,
      "region": "West",
      "prob_a": 0.4735,
      "prob_b": 0.5265
    },
    {
      "slot": 50,
      "teamA": "Prairie View A&M Panthers",
      "teamB": "Lehigh Mountain Hawks",
      "seedA": 16,
      "seedB": 16,
      "region": "South",
      "prob_a": 0.3799,
      "prob_b": 0.6201
    }
  ],
  "champion_probs": [
    [
      "Duke Blue Devils",
      0.1988
    ],
    [
      "Arizona Wildcats",
      0.142
    ],
    [
      "Michigan Wolverines",
      0.1262
    ],
    [
      "Gonzaga Bulldogs",
      0.0618
    ],
    [
      "Virginia Cavaliers",
      0.0338
    ],
    [
      "Arkansas Razorbacks",
      0.0264
    ],
    [
      "Iowa State Cyclones",
      0.0246
    ],
    [
      "BYU Cougars",
      0.0246
    ],
    [
      "St. John's Red Storm",
      0.0238
    ],
    [
      "Nebraska Cornhuskers",
      0.0234
    ],
    [
      "Florida Gators",
      0.023
    ],
    [
      "UConn Huskies",
      0.0224
    ],
    [
      "North Carolina Tar Heels",
      0.0212
    ],
    [
      "Saint Mary's Gaels",
      0.0204
    ],
    [
      "Vanderbilt Commodores",
      0.02
    ],
    [
      "Houston Cougars",
      0.017
    ],
    [
      "Saint Louis Billikens",
      0.016
    ],
    [
      "Michigan State Spartans",
      0.0158
    ],
    [
      "Alabama Crimson Tide",
      0.015
    ],
    [
      "VCU Rams",
      0.013
    ],
    [
      "Miami Hurricanes",
      0.0128
    ],
    [
      "Purdue Boilermakers",
      0.012
    ],
    [
      "Utah State Aggies",
      0.0116
    ],
    [
      "Kentucky Wildcats",
      0.0096
    ],
    [
      "Kansas Jayhawks",
      0.008
    ],
    [
      "Texas Tech Red Raiders",
      0.0074
    ],
    [
      "Illinois Fighting Illini",
      0.0074
    ],
    [
      "Louisville Cardinals",
      0.0056
    ],
    [
      "UCF Knights",
      0.0056
    ],
    [
      "McNeese Cowboys",
      0.005
    ],
    [
      "TCU Horned Frogs",
      0.0046
    ],
    [
      "Clemson Tigers",
      0.0046
    ],
    [
      "Santa Clara Broncos",
      0.0036
    ],
    [
      "Georgia Bulldogs",
      0.003
    ],
    [
      "Texas A&M Aggies",
      0.003
    ],
    [
      "South Florida Bulls",
      0.0028
    ],
    [
      "Villanova Wildcats",
      0.0026
    ],
    [
      "Akron Zips",
      0.0024
    ],
    [
      "Wisconsin Badgers",
      0.0024
    ],
    [
      "Miami OH RedHawks",
      0.0022
    ],
    [
      "Tennessee Volunteers",
      0.002
    ],
    [
      "High Point Panthers",
      0.0018
    ],
    [
      "Iowa Hawkeyes",
      0.0018
    ],
    [
      "UCLA Bruins",
      0.0016
    ],
    [
      "Ohio State Buckeyes",
      0.0012
    ],
    [
      "SMU Mustangs",
      0.001
    ],
    [
      "Missouri Tigers",
      0.001
    ],
    [
      "Hofstra Pride",
      0.0006
    ],
    [
      "California Baptist Lancers",
      0.0006
    ],
    [
      "North Dakota State Bison",
      0.0006
    ],
    [
      "Texas Longhorns",
      0.0006
    ],
    [
      "NC State Wolfpack",
      0.0006
    ],
    [
      "Tennessee State Tigers",
      0.0004
    ],
    [
      "Pennsylvania Quakers",
      0.0004
    ],
    [
      "Howard Bison",
      0.0002
    ],
    [
      "Troy Trojans",
      0.0002
    ],
    [
      "UMBC Retrievers",
      0.0
    ],
    [
      "Wright State Raiders",
      0.0
    ],
    [
      "Siena Saints",
      0.0
    ],
    [
      "Northern Iowa Panthers",
      0.0
    ],
    [
      "Furman Paladins",
      0.0
    ],
    [
      "Long Island University Sharks",
      0.0
    ],
    [
      "Hawai'i Rainbow Warriors",
      0.0
    ],
    [
      "Kennesaw State Owls",
      0.0
    ],
    [
      "Queens University Royals",
      0.0
    ],
    [
      "Prairie View A&M Panthers",
      0.0
    ],
    [
      "Lehigh Mountain Hawks",
      0.0
    ],
    [
      "Idaho Vandals",
      0.0
    ]
  ],
  "round_probs": {
    "Michigan Wolverines": {
      "champion": 0.1262,
      "elite_8": 0.4346,
      "final_4": 0.3146,
      "round_of_32": 0.859,
      "round_of_64": 1.0,
      "sweet_16": 0.5766,
      "title_game": 0.193
    },
    "UMBC Retrievers": {
      "elite_8": 0.003,
      "final_4": 0.0002,
      "first_four": 1.0,
      "round_of_32": 0.0898,
      "round_of_64": 0.6242,
      "sweet_16": 0.0154
    },
    "Howard Bison": {
      "champion": 0.0002,
      "elite_8": 0.0022,
      "final_4": 0.0006,
      "first_four": 1.0,
      "round_of_32": 0.0512,
      "round_of_64": 0.3758,
      "sweet_16": 0.0092,
      "title_game": 0.0002
    },
    "Georgia Bulldogs": {
      "champion": 0.003,
      "elite_8": 0.064,
      "final_4": 0.0266,
      "round_of_32": 0.373,
      "round_of_64": 1.0,
      "sweet_16": 0.1394,
      "title_game": 0.0094
    },
    "Saint Louis Billikens": {
      "champion": 0.016,
      "elite_8": 0.1452,
      "final_4": 0.0732,
      "round_of_32": 0.627,
      "round_of_64": 1.0,
      "sweet_16": 0.2594,
      "title_game": 0.0356
    },
    "Texas Tech Red Raiders": {
      "champion": 0.0074,
      "elite_8": 0.1058,
      "final_4": 0.0478,
      "round_of_32": 0.5838,
      "round_of_64": 1.0,
      "sweet_16": 0.2716,
      "title_game": 0.0188
    },
    "Akron Zips": {
      "champion": 0.0024,
      "elite_8": 0.0544,
      "final_4": 0.0198,
      "round_of_32": 0.4162,
      "round_of_64": 1.0,
      "sweet_16": 0.1726,
      "title_game": 0.0066
    },
    "Alabama Crimson Tide": {
      "champion": 0.015,
      "elite_8": 0.1768,
      "final_4": 0.0876,
      "round_of_32": 0.7692,
      "round_of_64": 1.0,
      "sweet_16": 0.4912,
      "title_game": 0.0354
    },
    "Hofstra Pride": {
      "champion": 0.0006,
      "elite_8": 0.014,
      "final_4": 0.0042,
      "round_of_32": 0.2308,
      "round_of_64": 1.0,
      "sweet_16": 0.0646,
      "title_game": 0.0012
    },
    "Tennessee Volunteers": {
      "champion": 0.002,
      "elite_8": 0.0766,
      "final_4": 0.0314,
      "round_of_32": 0.5522,
      "round_of_64": 1.0,
      "sweet_16": 0.1714,
      "title_game": 0.0094
    },
    "Miami OH RedHawks": {
      "champion": 0.0022,
      "elite_8": 0.0574,
      "final_4": 0.0208,
      "first_four": 1.0,
      "round_of_32": 0.3176,
      "round_of_64": 0.6906,
      "sweet_16": 0.1334,
      "title_game": 0.0076
    },
    "SMU Mustangs": {
      "champion": 0.001,
      "elite_8": 0.0202,
      "final_4": 0.0058,
      "first_four": 1.0,
      "round_of_32": 0.1302,
      "round_of_64": 0.3094,
      "sweet_16": 0.0546,
      "title_game": 0.0022
    },
    "Virginia Cavaliers": {
      "champion": 0.0338,
      "elite_8": 0.3176,
      "final_4": 0.1544,
      "round_of_32": 0.7942,
      "round_of_64": 1.0,
      "sweet_16": 0.586,
      "title_game": 0.0674
    },
    "Wright State Raiders": {
      "elite_8": 0.0144,
      "final_4": 0.0022,
      "round_of_32": 0.2058,
      "round_of_64": 1.0,
      "sweet_16": 0.0546,
      "title_game": 0.0002
    },
    "Kentucky Wildcats": {
      "champion": 0.0096,
      "elite_8": 0.1466,
      "final_4": 0.0618,
      "round_of_32": 0.5706,
      "round_of_64": 1.0,
      "sweet_16": 0.3102,
      "title_game": 0.0242
    },
    "Santa Clara Broncos": {
      "champion": 0.0036,
      "elite_8": 0.0982,
      "final_4": 0.0322,
      "round_of_32": 0.4294,
      "round_of_64": 1.0,
      "sweet_16": 0.2182,
      "title_game": 0.01
    },
    "Iowa State Cyclones": {
      "champion": 0.0246,
      "elite_8": 0.2472,
      "final_4": 0.111,
      "round_of_32": 0.7494,
      "round_of_64": 1.0,
      "sweet_16": 0.399,
      "title_game": 0.051
    },
    "Tennessee State Tigers": {
      "champion": 0.0004,
      "elite_8": 0.0218,
      "final_4": 0.0058,
      "round_of_32": 0.2506,
      "round_of_64": 1.0,
      "sweet_16": 0.0726,
      "title_game": 0.0016
    },
    "Duke Blue Devils": {
      "champion": 0.1988,
      "elite_8": 0.5228,
      "final_4": 0.4112,
      "round_of_32": 0.882,
      "round_of_64": 1.0,
      "sweet_16": 0.6984,
      "title_game": 0.284
    },
    "Siena Saints": {
      "elite_8": 0.0062,
      "final_4": 0.0006,
      "round_of_32": 0.118,
      "round_of_64": 1.0,
      "sweet_16": 0.0278
    },
    "Ohio State Buckeyes": {
      "champion": 0.0012,
      "elite_8": 0.0384,
      "final_4": 0.0136,
      "round_of_32": 0.4914,
      "round_of_64": 1.0,
      "sweet_16": 0.1204,
      "title_game": 0.004
    },
    "TCU Horned Frogs": {
      "champion": 0.0046,
      "elite_8": 0.0762,
      "final_4": 0.0348,
      "round_of_32": 0.5086,
      "round_of_64": 1.0,
      "sweet_16": 0.1534,
      "title_game": 0.0126
    },
    "St. John's Red Storm": {
      "champion": 0.0238,
      "elite_8": 0.184,
      "final_4": 0.1044,
      "round_of_32": 0.7332,
      "round_of_64": 1.0,
      "sweet_16": 0.4088,
      "title_game": 0.0522
    },
    "Northern Iowa Panthers": {
      "elite_8": 0.0206,
      "final_4": 0.0046,
      "round_of_32": 0.2668,
      "round_of_64": 1.0,
      "sweet_16": 0.0878,
      "title_game": 0.0008
    },
    "Kansas Jayhawks": {
      "champion": 0.008,
      "elite_8": 0.131,
      "final_4": 0.066,
      "round_of_32": 0.7018,
      "round_of_64": 1.0,
      "sweet_16": 0.4066,
      "title_game": 0.025
    },
    "California Baptist Lancers": {
      "champion": 0.0006,
      "elite_8": 0.0208,
      "final_4": 0.0076,
      "round_of_32": 0.2982,
      "round_of_64": 1.0,
      "sweet_16": 0.0968,
      "title_game": 0.002
    },
    "Louisville Cardinals": {
      "champion": 0.0056,
      "elite_8": 0.1342,
      "final_4": 0.0498,
      "round_of_32": 0.585,
      "round_of_64": 1.0,
      "sweet_16": 0.2664,
      "title_game": 0.0166
    },
    "South Florida Bulls": {
      "champion": 0.0028,
      "elite_8": 0.0926,
      "final_4": 0.0298,
      "round_of_32": 0.415,
      "round_of_64": 1.0,
      "sweet_16": 0.1872,
      "title_game": 0.0106
    },
    "Michigan State Spartans": {
      "champion": 0.0158,
      "elite_8": 0.2526,
      "final_4": 0.0982,
      "round_of_32": 0.7604,
      "round_of_64": 1.0,
      "sweet_16": 0.4842,
      "title_game": 0.0414
    },
    "North Dakota State Bison": {
      "champion": 0.0006,
      "elite_8": 0.023,
      "final_4": 0.0044,
      "round_of_32": 0.2396,
      "round_of_64": 1.0,
      "sweet_16": 0.0622,
      "title_game": 0.0016
    },
    "UCLA Bruins": {
      "champion": 0.0016,
      "elite_8": 0.0948,
      "final_4": 0.0272,
      "round_of_32": 0.572,
      "round_of_64": 1.0,
      "sweet_16": 0.247,
      "title_game": 0.008
    },
    "UCF Knights": {
      "champion": 0.0056,
      "elite_8": 0.0962,
      "final_4": 0.034,
      "round_of_32": 0.428,
      "round_of_64": 1.0,
      "sweet_16": 0.2098,
      "title_game": 0.0158
    },
    "UConn Huskies": {
      "champion": 0.0224,
      "elite_8": 0.2872,
      "final_4": 0.11,
      "round_of_32": 0.75,
      "round_of_64": 1.0,
      "sweet_16": 0.4604,
      "title_game": 0.05
    },
    "Furman Paladins": {
      "elite_8": 0.0194,
      "final_4": 0.0038,
      "round_of_32": 0.25,
      "round_of_64": 1.0,
      "sweet_16": 0.0828,
      "title_game": 0.0016
    },
    "Arizona Wildcats": {
      "champion": 0.142,
      "elite_8": 0.4988,
      "final_4": 0.3352,
      "round_of_32": 0.9076,
      "round_of_64": 1.0,
      "sweet_16": 0.6502,
      "title_game": 0.2472
    },
    "Long Island University Sharks": {
      "elite_8": 0.0022,
      "final_4": 0.0004,
      "round_of_32": 0.0924,
      "round_of_64": 1.0,
      "sweet_16": 0.0148
    },
    "Villanova Wildcats": {
      "champion": 0.0026,
      "elite_8": 0.0516,
      "final_4": 0.0206,
      "round_of_32": 0.3866,
      "round_of_64": 1.0,
      "sweet_16": 0.1216,
      "title_game": 0.008
    },
    "Utah State Aggies": {
      "champion": 0.0116,
      "elite_8": 0.1076,
      "final_4": 0.0526,
      "round_of_32": 0.6134,
      "round_of_64": 1.0,
      "sweet_16": 0.2134,
      "title_game": 0.0286
    },
    "Wisconsin Badgers": {
      "champion": 0.0024,
      "elite_8": 0.0598,
      "final_4": 0.0204,
      "round_of_32": 0.5298,
      "round_of_64": 1.0,
      "sweet_16": 0.1748,
      "title_game": 0.0066
    },
    "High Point Panthers": {
      "champion": 0.0018,
      "elite_8": 0.0428,
      "final_4": 0.0144,
      "round_of_32": 0.4702,
      "round_of_64": 1.0,
      "sweet_16": 0.1676,
      "title_game": 0.0058
    },
    "Arkansas Razorbacks": {
      "champion": 0.0264,
      "elite_8": 0.2308,
      "final_4": 0.11,
      "round_of_32": 0.851,
      "round_of_64": 1.0,
      "sweet_16": 0.6222,
      "title_game": 0.0632
    },
    "Hawai'i Rainbow Warriors": {
      "elite_8": 0.0064,
      "final_4": 0.0016,
      "round_of_32": 0.149,
      "round_of_64": 1.0,
      "sweet_16": 0.0354,
      "title_game": 0.0004
    },
    "BYU Cougars": {
      "champion": 0.0246,
      "elite_8": 0.2154,
      "final_4": 0.1036,
      "round_of_32": 0.7416,
      "round_of_64": 1.0,
      "sweet_16": 0.3578,
      "title_game": 0.0572
    },
    "Texas Longhorns": {
      "champion": 0.0006,
      "elite_8": 0.0144,
      "final_4": 0.0034,
      "first_four": 1.0,
      "round_of_32": 0.1378,
      "round_of_64": 0.4646,
      "sweet_16": 0.0498,
      "title_game": 0.0014
    },
    "NC State Wolfpack": {
      "champion": 0.0006,
      "elite_8": 0.0224,
      "final_4": 0.0066,
      "first_four": 1.0,
      "round_of_32": 0.1206,
      "round_of_64": 0.5354,
      "sweet_16": 0.052,
      "title_game": 0.002
    },
    "Gonzaga Bulldogs": {
      "champion": 0.0618,
      "elite_8": 0.3368,
      "final_4": 0.186,
      "round_of_32": 0.6976,
      "round_of_64": 1.0,
      "sweet_16": 0.4832,
      "title_game": 0.1168
    },
    "Kennesaw State Owls": {
      "elite_8": 0.0196,
      "final_4": 0.002,
      "round_of_32": 0.3024,
      "round_of_64": 1.0,
      "sweet_16": 0.0572,
      "title_game": 0.0004
    },
    "Miami Hurricanes": {
      "champion": 0.0128,
      "elite_8": 0.1634,
      "final_4": 0.0712,
      "round_of_32": 0.6692,
      "round_of_64": 1.0,
      "sweet_16": 0.383,
      "title_game": 0.0332
    },
    "Missouri Tigers": {
      "champion": 0.001,
      "elite_8": 0.055,
      "final_4": 0.011,
      "round_of_32": 0.3308,
      "round_of_64": 1.0,
      "sweet_16": 0.168,
      "title_game": 0.003
    },
    "Purdue Boilermakers": {
      "champion": 0.012,
      "elite_8": 0.159,
      "final_4": 0.0588,
      "round_of_32": 0.7116,
      "round_of_64": 1.0,
      "sweet_16": 0.375,
      "title_game": 0.0322
    },
    "Queens University Royals": {
      "elite_8": 0.014,
      "final_4": 0.0022,
      "round_of_32": 0.2884,
      "round_of_64": 1.0,
      "sweet_16": 0.074,
      "title_game": 0.0004
    },
    "Florida Gators": {
      "champion": 0.023,
      "elite_8": 0.2858,
      "final_4": 0.1586,
      "round_of_32": 0.8192,
      "round_of_64": 1.0,
      "sweet_16": 0.5048,
      "title_game": 0.0604
    },
    "Prairie View A&M Panthers": {
      "elite_8": 0.0016,
      "final_4": 0.0004,
      "first_four": 1.0,
      "round_of_32": 0.069,
      "round_of_64": 0.3796,
      "sweet_16": 0.012,
      "title_game": 0.0002
    },
    "Lehigh Mountain Hawks": {
      "elite_8": 0.0048,
      "first_four": 1.0,
      "round_of_32": 0.1118,
      "round_of_64": 0.6204,
      "sweet_16": 0.032
    },
    "Clemson Tigers": {
      "champion": 0.0046,
      "elite_8": 0.1164,
      "final_4": 0.044,
      "round_of_32": 0.6184,
      "round_of_64": 1.0,
      "sweet_16": 0.2858,
      "title_game": 0.0144
    },
    "Iowa Hawkeyes": {
      "champion": 0.0018,
      "elite_8": 0.057,
      "final_4": 0.0238,
      "round_of_32": 0.3816,
      "round_of_64": 1.0,
      "sweet_16": 0.1654,
      "title_game": 0.0074
    },
    "Vanderbilt Commodores": {
      "champion": 0.02,
      "elite_8": 0.1866,
      "final_4": 0.1016,
      "round_of_32": 0.64,
      "round_of_64": 1.0,
      "sweet_16": 0.3278,
      "title_game": 0.0416
    },
    "McNeese Cowboys": {
      "champion": 0.005,
      "elite_8": 0.0718,
      "final_4": 0.0308,
      "round_of_32": 0.36,
      "round_of_64": 1.0,
      "sweet_16": 0.1656,
      "title_game": 0.0098
    },
    "Nebraska Cornhuskers": {
      "champion": 0.0234,
      "elite_8": 0.2492,
      "final_4": 0.1386,
      "round_of_32": 0.7212,
      "round_of_64": 1.0,
      "sweet_16": 0.433,
      "title_game": 0.0514
    },
    "Troy Trojans": {
      "champion": 0.0002,
      "elite_8": 0.0268,
      "final_4": 0.009,
      "round_of_32": 0.2788,
      "round_of_64": 1.0,
      "sweet_16": 0.0736,
      "title_game": 0.0022
    },
    "North Carolina Tar Heels": {
      "champion": 0.0212,
      "elite_8": 0.1916,
      "final_4": 0.109,
      "round_of_32": 0.5692,
      "round_of_64": 1.0,
      "sweet_16": 0.3436,
      "title_game": 0.0478
    },
    "VCU Rams": {
      "champion": 0.013,
      "elite_8": 0.1438,
      "final_4": 0.0746,
      "round_of_32": 0.4308,
      "round_of_64": 1.0,
      "sweet_16": 0.2814,
      "title_game": 0.034
    },
    "Illinois Fighting Illini": {
      "champion": 0.0074,
      "elite_8": 0.1408,
      "final_4": 0.067,
      "round_of_32": 0.5456,
      "round_of_64": 1.0,
      "sweet_16": 0.2792,
      "title_game": 0.0248
    },
    "Pennsylvania Quakers": {
      "champion": 0.0004,
      "elite_8": 0.031,
      "final_4": 0.0068,
      "round_of_32": 0.4544,
      "round_of_64": 1.0,
      "sweet_16": 0.0958,
      "title_game": 0.0016
    },
    "Saint Mary's Gaels": {
      "champion": 0.0204,
      "elite_8": 0.2026,
      "final_4": 0.1032,
      "round_of_32": 0.6652,
      "round_of_64": 1.0,
      "sweet_16": 0.387,
      "title_game": 0.0468
    },
    "Texas A&M Aggies": {
      "champion": 0.003,
      "elite_8": 0.067,
      "final_4": 0.0228,
      "round_of_32": 0.3348,
      "round_of_64": 1.0,
      "sweet_16": 0.1778,
      "title_game": 0.0068
    },
    "Houston Cougars": {
      "champion": 0.017,
      "elite_8": 0.2098,
      "final_4": 0.1076,
      "round_of_32": 0.7164,
      "round_of_64": 1.0,
      "sweet_16": 0.3772,
      "title_game": 0.044
    },
    "Idaho Vandals": {
      "elite_8": 0.0134,
      "final_4": 0.0022,
      "round_of_32": 0.2836,
      "round_of_64": 1.0,
      "sweet_16": 0.058,
      "title_game": 0.0004
    }
  },
  "model_metadata": {
    "model_version": "lr+xgb+calibrated",
    "lr_model": true,
    "xgb_model": true,
    "lr_calibration": true,
    "xgb_calibration": true,
    "ensemble_weights": {
      "lr_weight": 0.0,
      "xgb_weight": 1.0
    },
    "seed_stratified_models": {
      "enabled": false,
      "source_dir": null,
      "loaded_strata": []
    },
    "feature_count": 19
  }
}